odoo10_addon_shopinvader_search_engine-10.0.1.2.1.99.dev3-py3.8-nspkg.pth
odoo/addons/shopinvader_search_engine/README.rst
odoo/addons/shopinvader_search_engine/__init__.py
odoo/addons/shopinvader_search_engine/__manifest__.py
odoo/addons/shopinvader_search_engine/data/ir_export_product.xml
odoo/addons/shopinvader_search_engine/i18n/shopinvader_search_engine.pot
odoo/addons/shopinvader_search_engine/models/__init__.py
odoo/addons/shopinvader_search_engine/models/se_index.py
odoo/addons/shopinvader_search_engine/models/shopinvader_backend.py
odoo/addons/shopinvader_search_engine/models/shopinvader_category.py
odoo/addons/shopinvader_search_engine/models/shopinvader_variant.py
odoo/addons/shopinvader_search_engine/tests/__init__.py
odoo/addons/shopinvader_search_engine/tests/test_action_server.py
odoo/addons/shopinvader_search_engine/tests/test_delete_product.py
odoo/addons/shopinvader_search_engine/views/product_category_view.xml
odoo/addons/shopinvader_search_engine/views/product_view.xml
odoo/addons/shopinvader_search_engine/views/shopinvader_backend_view.xml
odoo10_addon_shopinvader_search_engine-10.0.1.2.1.99.dev3.dist-info/METADATA
odoo10_addon_shopinvader_search_engine-10.0.1.2.1.99.dev3.dist-info/WHEEL
odoo10_addon_shopinvader_search_engine-10.0.1.2.1.99.dev3.dist-info/namespace_packages.txt
odoo10_addon_shopinvader_search_engine-10.0.1.2.1.99.dev3.dist-info/top_level.txt
odoo10_addon_shopinvader_search_engine-10.0.1.2.1.99.dev3.dist-info/RECORD
