Metadata-Version: 2.1
Name: odoo10-addon-shopinvader-search-engine
Version: 10.0.1.2.1.99.dev3
Summary: Shopinvader Catalog Search Engine Connector
Home-page: https://github.com/shopinvader/odoo-shopinvader
Author: Akretion
License: AGPL-3
Platform: UNKNOWN
Classifier: Programming Language :: Python
Classifier: Framework :: Odoo
Classifier: License :: OSI Approved :: GNU Affero General Public License v3
Requires-Python: ~=2.7
Requires-Dist: odoo10-addon-base-technical-user
Requires-Dist: odoo10-addon-connector-search-engine
Requires-Dist: odoo10-addon-shopinvader
Requires-Dist: odoo (<10.1dev,>=10.0)
